package wtf.opal;

import java.lang.invoke.MethodHandles;

public final class k0 {
  private static final long a = on.a(-4484032106149066992L, 7405548081389528115L, MethodHandles.lookup().lookupClass()).a(240098229691589L);
  
  public static boolean s(Object[] paramArrayOfObject) {
    // Byte code:
    //   0: aload_0
    //   1: dup
    //   2: iconst_0
    //   3: aaload
    //   4: checkcast net/minecraft/class_1309
    //   7: astore_1
    //   8: dup
    //   9: iconst_1
    //   10: aaload
    //   11: checkcast java/lang/Long
    //   14: invokevirtual longValue : ()J
    //   17: lstore_2
    //   18: pop
    //   19: getstatic wtf/opal/k0.a : J
    //   22: lload_2
    //   23: lxor
    //   24: lstore_2
    //   25: invokestatic P : ()Z
    //   28: iconst_0
    //   29: anewarray java/lang/Object
    //   32: invokestatic q : ([Ljava/lang/Object;)Lwtf/opal/d1;
    //   35: iconst_0
    //   36: anewarray java/lang/Object
    //   39: invokevirtual x : ([Ljava/lang/Object;)Lwtf/opal/x2;
    //   42: ldc wtf/opal/q
    //   44: iconst_1
    //   45: anewarray java/lang/Object
    //   48: dup_x1
    //   49: swap
    //   50: iconst_0
    //   51: swap
    //   52: aastore
    //   53: invokevirtual V : ([Ljava/lang/Object;)Lwtf/opal/d;
    //   56: checkcast wtf/opal/q
    //   59: astore #5
    //   61: istore #4
    //   63: aload_1
    //   64: invokevirtual method_6115 : ()Z
    //   67: iload #4
    //   69: ifeq -> 205
    //   72: ifne -> 204
    //   75: goto -> 82
    //   78: invokestatic a : (Lwtf/opal/x5;)Lwtf/opal/x5;
    //   81: athrow
    //   82: aload_1
    //   83: getstatic wtf/opal/b9.c : Lnet/minecraft/class_310;
    //   86: getfield field_1724 : Lnet/minecraft/class_746;
    //   89: if_acmpne -> 208
    //   92: goto -> 99
    //   95: invokestatic a : (Lwtf/opal/x5;)Lwtf/opal/x5;
    //   98: athrow
    //   99: aload #5
    //   101: iconst_0
    //   102: anewarray java/lang/Object
    //   105: invokevirtual D : ([Ljava/lang/Object;)Z
    //   108: iload #4
    //   110: lload_2
    //   111: lconst_0
    //   112: lcmp
    //   113: iflt -> 154
    //   116: ifeq -> 152
    //   119: goto -> 126
    //   122: invokestatic a : (Lwtf/opal/x5;)Lwtf/opal/x5;
    //   125: athrow
    //   126: ifeq -> 208
    //   129: goto -> 136
    //   132: invokestatic a : (Lwtf/opal/x5;)Lwtf/opal/x5;
    //   135: athrow
    //   136: aload #5
    //   138: iconst_0
    //   139: anewarray java/lang/Object
    //   142: invokevirtual K : ([Ljava/lang/Object;)Z
    //   145: goto -> 152
    //   148: invokestatic a : (Lwtf/opal/x5;)Lwtf/opal/x5;
    //   151: athrow
    //   152: iload #4
    //   154: lload_2
    //   155: lconst_0
    //   156: lcmp
    //   157: iflt -> 191
    //   160: ifeq -> 189
    //   163: ifeq -> 208
    //   166: goto -> 173
    //   169: invokestatic a : (Lwtf/opal/x5;)Lwtf/opal/x5;
    //   172: athrow
    //   173: aload #5
    //   175: iconst_0
    //   176: anewarray java/lang/Object
    //   179: invokevirtual Y : ([Ljava/lang/Object;)Z
    //   182: goto -> 189
    //   185: invokestatic a : (Lwtf/opal/x5;)Lwtf/opal/x5;
    //   188: athrow
    //   189: iload #4
    //   191: ifeq -> 205
    //   194: ifeq -> 208
    //   197: goto -> 204
    //   200: invokestatic a : (Lwtf/opal/x5;)Lwtf/opal/x5;
    //   203: athrow
    //   204: iconst_1
    //   205: goto -> 209
    //   208: iconst_0
    //   209: ireturn
    // Exception table:
    //   from	to	target	type
    //   63	75	78	wtf/opal/x5
    //   72	92	95	wtf/opal/x5
    //   82	119	122	wtf/opal/x5
    //   99	129	132	wtf/opal/x5
    //   126	145	148	wtf/opal/x5
    //   152	166	169	wtf/opal/x5
    //   163	182	185	wtf/opal/x5
    //   189	197	200	wtf/opal/x5
  }
  
  public static boolean J(Object[] paramArrayOfObject) {
    // Byte code:
    //   0: aload_0
    //   1: dup
    //   2: iconst_0
    //   3: aaload
    //   4: checkcast net/minecraft/class_1309
    //   7: astore #4
    //   9: dup
    //   10: iconst_1
    //   11: aaload
    //   12: checkcast java/lang/Integer
    //   15: invokevirtual intValue : ()I
    //   18: istore_3
    //   19: dup
    //   20: iconst_2
    //   21: aaload
    //   22: checkcast java/lang/Integer
    //   25: invokevirtual intValue : ()I
    //   28: istore_1
    //   29: dup
    //   30: iconst_3
    //   31: aaload
    //   32: checkcast java/lang/Integer
    //   35: invokevirtual intValue : ()I
    //   38: istore_2
    //   39: pop
    //   40: iload_3
    //   41: i2l
    //   42: bipush #48
    //   44: lshl
    //   45: iload_1
    //   46: i2l
    //   47: bipush #32
    //   49: lshl
    //   50: bipush #16
    //   52: lushr
    //   53: lor
    //   54: iload_2
    //   55: i2l
    //   56: bipush #48
    //   58: lshl
    //   59: bipush #48
    //   61: lushr
    //   62: lor
    //   63: getstatic wtf/opal/k0.a : J
    //   66: lxor
    //   67: lstore #5
    //   69: invokestatic Y : ()Z
    //   72: istore #7
    //   74: aload #4
    //   76: iload #7
    //   78: ifne -> 99
    //   81: ifnonnull -> 97
    //   84: goto -> 91
    //   87: invokestatic a : (Lwtf/opal/x5;)Lwtf/opal/x5;
    //   90: athrow
    //   91: iconst_0
    //   92: ireturn
    //   93: invokestatic a : (Lwtf/opal/x5;)Lwtf/opal/x5;
    //   96: athrow
    //   97: aload #4
    //   99: getstatic net/minecraft/class_1268.field_5808 : Lnet/minecraft/class_1268;
    //   102: invokevirtual method_5998 : (Lnet/minecraft/class_1268;)Lnet/minecraft/class_1799;
    //   105: astore #8
    //   107: aload #4
    //   109: getstatic net/minecraft/class_1268.field_5810 : Lnet/minecraft/class_1268;
    //   112: invokevirtual method_5998 : (Lnet/minecraft/class_1268;)Lnet/minecraft/class_1799;
    //   115: astore #9
    //   117: iload_2
    //   118: iflt -> 132
    //   121: aload #4
    //   123: getstatic wtf/opal/b9.c : Lnet/minecraft/class_310;
    //   126: getfield field_1724 : Lnet/minecraft/class_746;
    //   129: if_acmpeq -> 199
    //   132: aload #8
    //   134: invokevirtual method_7909 : ()Lnet/minecraft/class_1792;
    //   137: instanceof net/minecraft/class_1829
    //   140: iload #7
    //   142: iload_1
    //   143: iflt -> 180
    //   146: ifne -> 178
    //   149: goto -> 156
    //   152: invokestatic a : (Lwtf/opal/x5;)Lwtf/opal/x5;
    //   155: athrow
    //   156: ifeq -> 197
    //   159: goto -> 166
    //   162: invokestatic a : (Lwtf/opal/x5;)Lwtf/opal/x5;
    //   165: athrow
    //   166: aload #4
    //   168: invokevirtual method_6115 : ()Z
    //   171: goto -> 178
    //   174: invokestatic a : (Lwtf/opal/x5;)Lwtf/opal/x5;
    //   177: athrow
    //   178: iload #7
    //   180: ifne -> 194
    //   183: ifeq -> 197
    //   186: goto -> 193
    //   189: invokestatic a : (Lwtf/opal/x5;)Lwtf/opal/x5;
    //   192: athrow
    //   193: iconst_1
    //   194: goto -> 198
    //   197: iconst_0
    //   198: ireturn
    //   199: iconst_0
    //   200: anewarray java/lang/Object
    //   203: invokestatic q : ([Ljava/lang/Object;)Lwtf/opal/d1;
    //   206: iconst_0
    //   207: anewarray java/lang/Object
    //   210: invokevirtual x : ([Ljava/lang/Object;)Lwtf/opal/x2;
    //   213: ldc wtf/opal/q
    //   215: iconst_1
    //   216: anewarray java/lang/Object
    //   219: dup_x1
    //   220: swap
    //   221: iconst_0
    //   222: swap
    //   223: aastore
    //   224: invokevirtual V : ([Ljava/lang/Object;)Lwtf/opal/d;
    //   227: checkcast wtf/opal/q
    //   230: astore #10
    //   232: iconst_0
    //   233: anewarray java/lang/Object
    //   236: invokestatic q : ([Ljava/lang/Object;)Lwtf/opal/d1;
    //   239: iconst_0
    //   240: anewarray java/lang/Object
    //   243: invokevirtual x : ([Ljava/lang/Object;)Lwtf/opal/x2;
    //   246: ldc wtf/opal/je
    //   248: iconst_1
    //   249: anewarray java/lang/Object
    //   252: dup_x1
    //   253: swap
    //   254: iconst_0
    //   255: swap
    //   256: aastore
    //   257: invokevirtual V : ([Ljava/lang/Object;)Lwtf/opal/d;
    //   260: checkcast wtf/opal/je
    //   263: astore #11
    //   265: aload #10
    //   267: iconst_0
    //   268: anewarray java/lang/Object
    //   271: invokevirtual D : ([Ljava/lang/Object;)Z
    //   274: iload #7
    //   276: iload_3
    //   277: iflt -> 311
    //   280: ifne -> 309
    //   283: ifeq -> 363
    //   286: goto -> 293
    //   289: invokestatic a : (Lwtf/opal/x5;)Lwtf/opal/x5;
    //   292: athrow
    //   293: aload #10
    //   295: iconst_0
    //   296: anewarray java/lang/Object
    //   299: invokevirtual K : ([Ljava/lang/Object;)Z
    //   302: goto -> 309
    //   305: invokestatic a : (Lwtf/opal/x5;)Lwtf/opal/x5;
    //   308: athrow
    //   309: iload #7
    //   311: iload_1
    //   312: ifle -> 346
    //   315: ifne -> 344
    //   318: ifeq -> 363
    //   321: goto -> 328
    //   324: invokestatic a : (Lwtf/opal/x5;)Lwtf/opal/x5;
    //   327: athrow
    //   328: aload #10
    //   330: iconst_0
    //   331: anewarray java/lang/Object
    //   334: invokevirtual Y : ([Ljava/lang/Object;)Z
    //   337: goto -> 344
    //   340: invokestatic a : (Lwtf/opal/x5;)Lwtf/opal/x5;
    //   343: athrow
    //   344: iload #7
    //   346: ifne -> 360
    //   349: ifeq -> 363
    //   352: goto -> 359
    //   355: invokestatic a : (Lwtf/opal/x5;)Lwtf/opal/x5;
    //   358: athrow
    //   359: iconst_1
    //   360: goto -> 364
    //   363: iconst_0
    //   364: istore #12
    //   366: aload #8
    //   368: invokevirtual method_7909 : ()Lnet/minecraft/class_1792;
    //   371: instanceof net/minecraft/class_1829
    //   374: iload #7
    //   376: iload_1
    //   377: ifle -> 397
    //   380: ifne -> 395
    //   383: ifeq -> 586
    //   386: goto -> 393
    //   389: invokestatic a : (Lwtf/opal/x5;)Lwtf/opal/x5;
    //   392: athrow
    //   393: iload #12
    //   395: iload #7
    //   397: ifne -> 477
    //   400: ifne -> 475
    //   403: goto -> 410
    //   406: invokestatic a : (Lwtf/opal/x5;)Lwtf/opal/x5;
    //   409: athrow
    //   410: aload #11
    //   412: iconst_0
    //   413: anewarray java/lang/Object
    //   416: invokevirtual A : ([Ljava/lang/Object;)Z
    //   419: iload #7
    //   421: ifne -> 477
    //   424: goto -> 431
    //   427: invokestatic a : (Lwtf/opal/x5;)Lwtf/opal/x5;
    //   430: athrow
    //   431: ifne -> 475
    //   434: goto -> 441
    //   437: invokestatic a : (Lwtf/opal/x5;)Lwtf/opal/x5;
    //   440: athrow
    //   441: aload #9
    //   443: invokevirtual method_7909 : ()Lnet/minecraft/class_1792;
    //   446: instanceof net/minecraft/class_1819
    //   449: iload #7
    //   451: iload_3
    //   452: iflt -> 479
    //   455: ifne -> 477
    //   458: goto -> 465
    //   461: invokestatic a : (Lwtf/opal/x5;)Lwtf/opal/x5;
    //   464: athrow
    //   465: ifeq -> 586
    //   468: goto -> 475
    //   471: invokestatic a : (Lwtf/opal/x5;)Lwtf/opal/x5;
    //   474: athrow
    //   475: iload #12
    //   477: iload #7
    //   479: ifne -> 583
    //   482: ifne -> 575
    //   485: goto -> 492
    //   488: invokestatic a : (Lwtf/opal/x5;)Lwtf/opal/x5;
    //   491: athrow
    //   492: aload #4
    //   494: invokevirtual method_6115 : ()Z
    //   497: iload #7
    //   499: ifne -> 583
    //   502: goto -> 509
    //   505: invokestatic a : (Lwtf/opal/x5;)Lwtf/opal/x5;
    //   508: athrow
    //   509: iload_2
    //   510: iflt -> 576
    //   513: ifne -> 575
    //   516: goto -> 523
    //   519: invokestatic a : (Lwtf/opal/x5;)Lwtf/opal/x5;
    //   522: athrow
    //   523: aload #4
    //   525: iload_3
    //   526: iflt -> 563
    //   529: iload #7
    //   531: ifne -> 563
    //   534: goto -> 541
    //   537: invokestatic a : (Lwtf/opal/x5;)Lwtf/opal/x5;
    //   540: athrow
    //   541: invokevirtual method_6048 : ()I
    //   544: ifle -> 586
    //   547: goto -> 554
    //   550: invokestatic a : (Lwtf/opal/x5;)Lwtf/opal/x5;
    //   553: athrow
    //   554: aload #4
    //   556: goto -> 563
    //   559: invokestatic a : (Lwtf/opal/x5;)Lwtf/opal/x5;
    //   562: athrow
    //   563: invokevirtual method_6079 : ()Lnet/minecraft/class_1799;
    //   566: invokevirtual method_7976 : ()Lnet/minecraft/class_1839;
    //   569: getstatic net/minecraft/class_1839.field_8949 : Lnet/minecraft/class_1839;
    //   572: if_acmpne -> 586
    //   575: iconst_1
    //   576: goto -> 583
    //   579: invokestatic a : (Lwtf/opal/x5;)Lwtf/opal/x5;
    //   582: athrow
    //   583: goto -> 587
    //   586: iconst_0
    //   587: ireturn
    // Exception table:
    //   from	to	target	type
    //   74	84	87	wtf/opal/x5
    //   81	93	93	wtf/opal/x5
    //   117	149	152	wtf/opal/x5
    //   132	159	162	wtf/opal/x5
    //   156	171	174	wtf/opal/x5
    //   178	186	189	wtf/opal/x5
    //   265	286	289	wtf/opal/x5
    //   283	302	305	wtf/opal/x5
    //   309	321	324	wtf/opal/x5
    //   318	337	340	wtf/opal/x5
    //   344	352	355	wtf/opal/x5
    //   366	386	389	wtf/opal/x5
    //   395	403	406	wtf/opal/x5
    //   400	424	427	wtf/opal/x5
    //   410	434	437	wtf/opal/x5
    //   431	458	461	wtf/opal/x5
    //   441	468	471	wtf/opal/x5
    //   477	485	488	wtf/opal/x5
    //   482	502	505	wtf/opal/x5
    //   492	516	519	wtf/opal/x5
    //   509	534	537	wtf/opal/x5
    //   523	547	550	wtf/opal/x5
    //   541	556	559	wtf/opal/x5
    //   563	576	579	wtf/opal/x5
  }
  
  private static x5 a(x5 paramx5) {
    return paramx5;
  }
}


/* Location:              C:\Users\Administrator\Downloads\Opal 080624 ez\Opal.jar!\wtf\opal\k0.class
 * Java compiler version: 21 (65.0)
 * JD-Core Version:       1.1.3
 */