package wtf.opal;

import java.lang.invoke.MethodHandles;
import java.util.HashMap;
import java.util.Map;
import javax.crypto.Cipher;
import javax.crypto.SecretKeyFactory;
import javax.crypto.spec.DESKeySpec;
import javax.crypto.spec.IvParameterSpec;

public final class lj {
  private final Map<k6, d> X = new HashMap<>();
  
  private static final long a = on.a(-832193748330932008L, -2295749871378563726L, MethodHandles.lookup().lookupClass()).a(193729557625707L);
  
  private static final long b;
  
  public void A(Object[] paramArrayOfObject) {
    d d = (d)paramArrayOfObject[0];
    k6 k6 = (k6)paramArrayOfObject[1];
    this.X.put(k6, d);
  }
  
  public void u(Object[] paramArrayOfObject) {
    // Byte code:
    //   0: aload_1
    //   1: dup
    //   2: iconst_0
    //   3: aaload
    //   4: checkcast java/lang/Integer
    //   7: invokevirtual intValue : ()I
    //   10: istore #4
    //   12: dup
    //   13: iconst_1
    //   14: aaload
    //   15: checkcast java/lang/Long
    //   18: invokevirtual longValue : ()J
    //   21: lstore_2
    //   22: dup
    //   23: iconst_2
    //   24: aaload
    //   25: checkcast java/lang/Integer
    //   28: invokevirtual intValue : ()I
    //   31: istore #5
    //   33: pop
    //   34: getstatic wtf/opal/lj.a : J
    //   37: lload_2
    //   38: lxor
    //   39: lstore_2
    //   40: lload_2
    //   41: dup2
    //   42: ldc2_w 47195714730346
    //   45: lxor
    //   46: lstore #6
    //   48: dup2
    //   49: ldc2_w 85650008914764
    //   52: lxor
    //   53: lstore #8
    //   55: dup2
    //   56: ldc2_w 19142631654050
    //   59: lxor
    //   60: lstore #10
    //   62: dup2
    //   63: ldc2_w 33040538173067
    //   66: lxor
    //   67: lstore #12
    //   69: dup2
    //   70: ldc2_w 133997474582837
    //   73: lxor
    //   74: lstore #14
    //   76: dup2
    //   77: ldc2_w 105815538273359
    //   80: lxor
    //   81: lstore #16
    //   83: pop2
    //   84: invokestatic d : ()Z
    //   87: aload_0
    //   88: getfield X : Ljava/util/Map;
    //   91: invokeinterface entrySet : ()Ljava/util/Set;
    //   96: invokeinterface iterator : ()Ljava/util/Iterator;
    //   101: astore #22
    //   103: istore #21
    //   105: aload #22
    //   107: invokeinterface hasNext : ()Z
    //   112: ifeq -> 866
    //   115: aload #22
    //   117: invokeinterface next : ()Ljava/lang/Object;
    //   122: checkcast java/util/Map$Entry
    //   125: astore #23
    //   127: aload #23
    //   129: invokeinterface getValue : ()Ljava/lang/Object;
    //   134: checkcast wtf/opal/d
    //   137: iload #21
    //   139: lload_2
    //   140: lconst_0
    //   141: lcmp
    //   142: ifle -> 149
    //   145: ifeq -> 185
    //   148: iconst_0
    //   149: anewarray java/lang/Object
    //   152: invokevirtual D : ([Ljava/lang/Object;)Z
    //   155: lload_2
    //   156: lconst_0
    //   157: lcmp
    //   158: iflt -> 863
    //   161: ifeq -> 861
    //   164: goto -> 171
    //   167: invokestatic a : (Lwtf/opal/x5;)Lwtf/opal/x5;
    //   170: athrow
    //   171: aload #23
    //   173: invokeinterface getKey : ()Ljava/lang/Object;
    //   178: goto -> 185
    //   181: invokestatic a : (Lwtf/opal/x5;)Lwtf/opal/x5;
    //   184: athrow
    //   185: checkcast wtf/opal/k6
    //   188: astore #24
    //   190: aload #24
    //   192: iconst_0
    //   193: anewarray java/lang/Object
    //   196: invokevirtual A : ([Ljava/lang/Object;)Z
    //   199: lload_2
    //   200: lconst_0
    //   201: lcmp
    //   202: iflt -> 434
    //   205: iload #21
    //   207: ifeq -> 434
    //   210: ifeq -> 309
    //   213: goto -> 220
    //   216: invokestatic a : (Lwtf/opal/x5;)Lwtf/opal/x5;
    //   219: athrow
    //   220: aload #24
    //   222: iload #4
    //   224: i2f
    //   225: aload #24
    //   227: lload #8
    //   229: iconst_1
    //   230: anewarray java/lang/Object
    //   233: dup_x2
    //   234: dup_x2
    //   235: pop
    //   236: invokestatic valueOf : (J)Ljava/lang/Long;
    //   239: iconst_0
    //   240: swap
    //   241: aastore
    //   242: invokevirtual z : ([Ljava/lang/Object;)F
    //   245: fsub
    //   246: lload #12
    //   248: iconst_2
    //   249: anewarray java/lang/Object
    //   252: dup_x2
    //   253: dup_x2
    //   254: pop
    //   255: invokestatic valueOf : (J)Ljava/lang/Long;
    //   258: iconst_1
    //   259: swap
    //   260: aastore
    //   261: dup_x1
    //   262: swap
    //   263: invokestatic valueOf : (F)Ljava/lang/Float;
    //   266: iconst_0
    //   267: swap
    //   268: aastore
    //   269: invokevirtual X : ([Ljava/lang/Object;)V
    //   272: aload #24
    //   274: iload #5
    //   276: i2f
    //   277: aload #24
    //   279: iconst_0
    //   280: anewarray java/lang/Object
    //   283: invokevirtual h : ([Ljava/lang/Object;)F
    //   286: fsub
    //   287: iconst_1
    //   288: anewarray java/lang/Object
    //   291: dup_x1
    //   292: swap
    //   293: invokestatic valueOf : (F)Ljava/lang/Float;
    //   296: iconst_0
    //   297: swap
    //   298: aastore
    //   299: invokevirtual q : ([Ljava/lang/Object;)V
    //   302: goto -> 309
    //   305: invokestatic a : (Lwtf/opal/x5;)Lwtf/opal/x5;
    //   308: athrow
    //   309: aload #24
    //   311: lload #14
    //   313: iconst_1
    //   314: anewarray java/lang/Object
    //   317: dup_x2
    //   318: dup_x2
    //   319: pop
    //   320: invokestatic valueOf : (J)Ljava/lang/Long;
    //   323: iconst_0
    //   324: swap
    //   325: aastore
    //   326: invokevirtual t : ([Ljava/lang/Object;)F
    //   329: lload #6
    //   331: dup2_x1
    //   332: pop2
    //   333: aload #24
    //   335: iconst_0
    //   336: anewarray java/lang/Object
    //   339: invokevirtual x : ([Ljava/lang/Object;)F
    //   342: aload #24
    //   344: iconst_0
    //   345: anewarray java/lang/Object
    //   348: invokevirtual K : ([Ljava/lang/Object;)F
    //   351: aload #24
    //   353: iconst_0
    //   354: anewarray java/lang/Object
    //   357: invokevirtual p : ([Ljava/lang/Object;)F
    //   360: iload #4
    //   362: i2d
    //   363: iload #5
    //   365: i2d
    //   366: bipush #7
    //   368: anewarray java/lang/Object
    //   371: dup_x2
    //   372: dup_x2
    //   373: pop
    //   374: invokestatic valueOf : (D)Ljava/lang/Double;
    //   377: bipush #6
    //   379: swap
    //   380: aastore
    //   381: dup_x2
    //   382: dup_x2
    //   383: pop
    //   384: invokestatic valueOf : (D)Ljava/lang/Double;
    //   387: iconst_5
    //   388: swap
    //   389: aastore
    //   390: dup_x1
    //   391: swap
    //   392: invokestatic valueOf : (F)Ljava/lang/Float;
    //   395: iconst_4
    //   396: swap
    //   397: aastore
    //   398: dup_x1
    //   399: swap
    //   400: invokestatic valueOf : (F)Ljava/lang/Float;
    //   403: iconst_3
    //   404: swap
    //   405: aastore
    //   406: dup_x1
    //   407: swap
    //   408: invokestatic valueOf : (F)Ljava/lang/Float;
    //   411: iconst_2
    //   412: swap
    //   413: aastore
    //   414: dup_x1
    //   415: swap
    //   416: invokestatic valueOf : (F)Ljava/lang/Float;
    //   419: iconst_1
    //   420: swap
    //   421: aastore
    //   422: dup_x2
    //   423: dup_x2
    //   424: pop
    //   425: invokestatic valueOf : (J)Ljava/lang/Long;
    //   428: iconst_0
    //   429: swap
    //   430: aastore
    //   431: invokestatic Z : ([Ljava/lang/Object;)Z
    //   434: lload_2
    //   435: lconst_0
    //   436: lcmp
    //   437: ifle -> 863
    //   440: ifeq -> 861
    //   443: iconst_0
    //   444: anewarray java/lang/Object
    //   447: invokestatic q : ([Ljava/lang/Object;)Lwtf/opal/d1;
    //   450: iconst_0
    //   451: anewarray java/lang/Object
    //   454: invokevirtual z : ([Ljava/lang/Object;)Lwtf/opal/pa;
    //   457: aload #24
    //   459: lload #14
    //   461: iconst_1
    //   462: anewarray java/lang/Object
    //   465: dup_x2
    //   466: dup_x2
    //   467: pop
    //   468: invokestatic valueOf : (J)Ljava/lang/Long;
    //   471: iconst_0
    //   472: swap
    //   473: aastore
    //   474: invokevirtual t : ([Ljava/lang/Object;)F
    //   477: fconst_2
    //   478: fsub
    //   479: aload #24
    //   481: iconst_0
    //   482: anewarray java/lang/Object
    //   485: invokevirtual x : ([Ljava/lang/Object;)F
    //   488: fconst_2
    //   489: fsub
    //   490: aload #24
    //   492: iconst_0
    //   493: anewarray java/lang/Object
    //   496: invokevirtual K : ([Ljava/lang/Object;)F
    //   499: ldc 4.0
    //   501: fadd
    //   502: aload #24
    //   504: iconst_0
    //   505: anewarray java/lang/Object
    //   508: invokevirtual p : ([Ljava/lang/Object;)F
    //   511: ldc 4.0
    //   513: fadd
    //   514: aload #24
    //   516: iconst_0
    //   517: anewarray java/lang/Object
    //   520: invokevirtual D : ([Ljava/lang/Object;)F
    //   523: fconst_0
    //   524: iload #21
    //   526: ifeq -> 565
    //   529: goto -> 536
    //   532: invokestatic a : (Lwtf/opal/x5;)Lwtf/opal/x5;
    //   535: athrow
    //   536: fcmpl
    //   537: ifne -> 555
    //   540: goto -> 547
    //   543: invokestatic a : (Lwtf/opal/x5;)Lwtf/opal/x5;
    //   546: athrow
    //   547: fconst_0
    //   548: goto -> 566
    //   551: invokestatic a : (Lwtf/opal/x5;)Lwtf/opal/x5;
    //   554: athrow
    //   555: aload #24
    //   557: iconst_0
    //   558: anewarray java/lang/Object
    //   561: invokevirtual D : ([Ljava/lang/Object;)F
    //   564: fconst_1
    //   565: fadd
    //   566: fconst_1
    //   567: iconst_m1
    //   568: ldc 0.75
    //   570: iconst_2
    //   571: anewarray java/lang/Object
    //   574: dup_x1
    //   575: swap
    //   576: invokestatic valueOf : (F)Ljava/lang/Float;
    //   579: iconst_1
    //   580: swap
    //   581: aastore
    //   582: dup_x1
    //   583: swap
    //   584: invokestatic valueOf : (I)Ljava/lang/Integer;
    //   587: iconst_0
    //   588: swap
    //   589: aastore
    //   590: invokestatic X : ([Ljava/lang/Object;)I
    //   593: istore #18
    //   595: fstore #19
    //   597: fstore #20
    //   599: lload #16
    //   601: fload #20
    //   603: fload #19
    //   605: iload #18
    //   607: bipush #8
    //   609: anewarray java/lang/Object
    //   612: dup_x1
    //   613: swap
    //   614: invokestatic valueOf : (I)Ljava/lang/Integer;
    //   617: bipush #7
    //   619: swap
    //   620: aastore
    //   621: dup_x1
    //   622: swap
    //   623: invokestatic valueOf : (F)Ljava/lang/Float;
    //   626: bipush #6
    //   628: swap
    //   629: aastore
    //   630: dup_x1
    //   631: swap
    //   632: invokestatic valueOf : (F)Ljava/lang/Float;
    //   635: iconst_5
    //   636: swap
    //   637: aastore
    //   638: dup_x2
    //   639: dup_x2
    //   640: pop
    //   641: invokestatic valueOf : (J)Ljava/lang/Long;
    //   644: iconst_4
    //   645: swap
    //   646: aastore
    //   647: dup_x1
    //   648: swap
    //   649: invokestatic valueOf : (F)Ljava/lang/Float;
    //   652: iconst_3
    //   653: swap
    //   654: aastore
    //   655: dup_x1
    //   656: swap
    //   657: invokestatic valueOf : (F)Ljava/lang/Float;
    //   660: iconst_2
    //   661: swap
    //   662: aastore
    //   663: dup_x1
    //   664: swap
    //   665: invokestatic valueOf : (F)Ljava/lang/Float;
    //   668: iconst_1
    //   669: swap
    //   670: aastore
    //   671: dup_x1
    //   672: swap
    //   673: invokestatic valueOf : (F)Ljava/lang/Float;
    //   676: iconst_0
    //   677: swap
    //   678: aastore
    //   679: invokevirtual G : ([Ljava/lang/Object;)V
    //   682: iconst_0
    //   683: anewarray java/lang/Object
    //   686: invokestatic q : ([Ljava/lang/Object;)Lwtf/opal/d1;
    //   689: iconst_0
    //   690: anewarray java/lang/Object
    //   693: invokevirtual z : ([Ljava/lang/Object;)Lwtf/opal/pa;
    //   696: aload #24
    //   698: lload #14
    //   700: iconst_1
    //   701: anewarray java/lang/Object
    //   704: dup_x2
    //   705: dup_x2
    //   706: pop
    //   707: invokestatic valueOf : (J)Ljava/lang/Long;
    //   710: iconst_0
    //   711: swap
    //   712: aastore
    //   713: invokevirtual t : ([Ljava/lang/Object;)F
    //   716: ldc 2.5
    //   718: fsub
    //   719: aload #24
    //   721: iconst_0
    //   722: anewarray java/lang/Object
    //   725: invokevirtual x : ([Ljava/lang/Object;)F
    //   728: ldc 2.5
    //   730: fsub
    //   731: aload #24
    //   733: iconst_0
    //   734: anewarray java/lang/Object
    //   737: invokevirtual K : ([Ljava/lang/Object;)F
    //   740: ldc 4.5
    //   742: fadd
    //   743: aload #24
    //   745: iconst_0
    //   746: anewarray java/lang/Object
    //   749: invokevirtual p : ([Ljava/lang/Object;)F
    //   752: ldc 4.5
    //   754: fadd
    //   755: aload #24
    //   757: iconst_0
    //   758: anewarray java/lang/Object
    //   761: invokevirtual D : ([Ljava/lang/Object;)F
    //   764: getstatic wtf/opal/lj.b : J
    //   767: l2i
    //   768: ldc 0.3
    //   770: iconst_2
    //   771: anewarray java/lang/Object
    //   774: dup_x1
    //   775: swap
    //   776: invokestatic valueOf : (F)Ljava/lang/Float;
    //   779: iconst_1
    //   780: swap
    //   781: aastore
    //   782: dup_x1
    //   783: swap
    //   784: invokestatic valueOf : (I)Ljava/lang/Integer;
    //   787: iconst_0
    //   788: swap
    //   789: aastore
    //   790: invokestatic X : ([Ljava/lang/Object;)I
    //   793: lload #10
    //   795: bipush #7
    //   797: anewarray java/lang/Object
    //   800: dup_x2
    //   801: dup_x2
    //   802: pop
    //   803: invokestatic valueOf : (J)Ljava/lang/Long;
    //   806: bipush #6
    //   808: swap
    //   809: aastore
    //   810: dup_x1
    //   811: swap
    //   812: invokestatic valueOf : (I)Ljava/lang/Integer;
    //   815: iconst_5
    //   816: swap
    //   817: aastore
    //   818: dup_x1
    //   819: swap
    //   820: invokestatic valueOf : (F)Ljava/lang/Float;
    //   823: iconst_4
    //   824: swap
    //   825: aastore
    //   826: dup_x1
    //   827: swap
    //   828: invokestatic valueOf : (F)Ljava/lang/Float;
    //   831: iconst_3
    //   832: swap
    //   833: aastore
    //   834: dup_x1
    //   835: swap
    //   836: invokestatic valueOf : (F)Ljava/lang/Float;
    //   839: iconst_2
    //   840: swap
    //   841: aastore
    //   842: dup_x1
    //   843: swap
    //   844: invokestatic valueOf : (F)Ljava/lang/Float;
    //   847: iconst_1
    //   848: swap
    //   849: aastore
    //   850: dup_x1
    //   851: swap
    //   852: invokestatic valueOf : (F)Ljava/lang/Float;
    //   855: iconst_0
    //   856: swap
    //   857: aastore
    //   858: invokevirtual M : ([Ljava/lang/Object;)V
    //   861: iload #21
    //   863: ifne -> 105
    //   866: return
    // Exception table:
    //   from	to	target	type
    //   127	164	167	wtf/opal/x5
    //   148	178	181	wtf/opal/x5
    //   190	213	216	wtf/opal/x5
    //   210	302	305	wtf/opal/x5
    //   434	529	532	wtf/opal/x5
    //   443	540	543	wtf/opal/x5
    //   536	551	551	wtf/opal/x5
  }
  
  public void H(Object[] paramArrayOfObject) {
    // Byte code:
    //   0: aload_1
    //   1: dup
    //   2: iconst_0
    //   3: aaload
    //   4: checkcast java/lang/Double
    //   7: invokevirtual doubleValue : ()D
    //   10: dstore_3
    //   11: dup
    //   12: iconst_1
    //   13: aaload
    //   14: checkcast java/lang/Double
    //   17: invokevirtual doubleValue : ()D
    //   20: dstore #5
    //   22: dup
    //   23: iconst_2
    //   24: aaload
    //   25: checkcast java/lang/Integer
    //   28: invokevirtual intValue : ()I
    //   31: istore_2
    //   32: dup
    //   33: iconst_3
    //   34: aaload
    //   35: checkcast java/lang/Long
    //   38: invokevirtual longValue : ()J
    //   41: lstore #7
    //   43: pop
    //   44: getstatic wtf/opal/lj.a : J
    //   47: lload #7
    //   49: lxor
    //   50: lstore #7
    //   52: lload #7
    //   54: dup2
    //   55: ldc2_w 102566431698544
    //   58: lxor
    //   59: lstore #9
    //   61: dup2
    //   62: ldc2_w 15920230172207
    //   65: lxor
    //   66: lstore #11
    //   68: pop2
    //   69: invokestatic e : ()Z
    //   72: istore #13
    //   74: iload_2
    //   75: ifeq -> 83
    //   78: return
    //   79: invokestatic a : (Lwtf/opal/x5;)Lwtf/opal/x5;
    //   82: athrow
    //   83: aload_0
    //   84: getfield X : Ljava/util/Map;
    //   87: invokeinterface entrySet : ()Ljava/util/Set;
    //   92: invokeinterface iterator : ()Ljava/util/Iterator;
    //   97: astore #14
    //   99: aload #14
    //   101: invokeinterface hasNext : ()Z
    //   106: ifeq -> 432
    //   109: aload #14
    //   111: invokeinterface next : ()Ljava/lang/Object;
    //   116: checkcast java/util/Map$Entry
    //   119: astore #15
    //   121: aload #15
    //   123: invokeinterface getValue : ()Ljava/lang/Object;
    //   128: checkcast wtf/opal/d
    //   131: iload #13
    //   133: lload #7
    //   135: lconst_0
    //   136: lcmp
    //   137: iflt -> 144
    //   140: ifne -> 181
    //   143: iconst_0
    //   144: anewarray java/lang/Object
    //   147: invokevirtual D : ([Ljava/lang/Object;)Z
    //   150: lload #7
    //   152: lconst_0
    //   153: lcmp
    //   154: ifle -> 429
    //   157: ifeq -> 427
    //   160: goto -> 167
    //   163: invokestatic a : (Lwtf/opal/x5;)Lwtf/opal/x5;
    //   166: athrow
    //   167: aload #15
    //   169: invokeinterface getKey : ()Ljava/lang/Object;
    //   174: goto -> 181
    //   177: invokestatic a : (Lwtf/opal/x5;)Lwtf/opal/x5;
    //   180: athrow
    //   181: checkcast wtf/opal/k6
    //   184: astore #16
    //   186: aload #16
    //   188: iload #13
    //   190: ifne -> 398
    //   193: lload #11
    //   195: iconst_1
    //   196: anewarray java/lang/Object
    //   199: dup_x2
    //   200: dup_x2
    //   201: pop
    //   202: invokestatic valueOf : (J)Ljava/lang/Long;
    //   205: iconst_0
    //   206: swap
    //   207: aastore
    //   208: invokevirtual t : ([Ljava/lang/Object;)F
    //   211: lload #9
    //   213: dup2_x1
    //   214: pop2
    //   215: aload #16
    //   217: iconst_0
    //   218: anewarray java/lang/Object
    //   221: invokevirtual x : ([Ljava/lang/Object;)F
    //   224: aload #16
    //   226: iconst_0
    //   227: anewarray java/lang/Object
    //   230: invokevirtual K : ([Ljava/lang/Object;)F
    //   233: aload #16
    //   235: iconst_0
    //   236: anewarray java/lang/Object
    //   239: invokevirtual p : ([Ljava/lang/Object;)F
    //   242: dload_3
    //   243: dload #5
    //   245: bipush #7
    //   247: anewarray java/lang/Object
    //   250: dup_x2
    //   251: dup_x2
    //   252: pop
    //   253: invokestatic valueOf : (D)Ljava/lang/Double;
    //   256: bipush #6
    //   258: swap
    //   259: aastore
    //   260: dup_x2
    //   261: dup_x2
    //   262: pop
    //   263: invokestatic valueOf : (D)Ljava/lang/Double;
    //   266: iconst_5
    //   267: swap
    //   268: aastore
    //   269: dup_x1
    //   270: swap
    //   271: invokestatic valueOf : (F)Ljava/lang/Float;
    //   274: iconst_4
    //   275: swap
    //   276: aastore
    //   277: dup_x1
    //   278: swap
    //   279: invokestatic valueOf : (F)Ljava/lang/Float;
    //   282: iconst_3
    //   283: swap
    //   284: aastore
    //   285: dup_x1
    //   286: swap
    //   287: invokestatic valueOf : (F)Ljava/lang/Float;
    //   290: iconst_2
    //   291: swap
    //   292: aastore
    //   293: dup_x1
    //   294: swap
    //   295: invokestatic valueOf : (F)Ljava/lang/Float;
    //   298: iconst_1
    //   299: swap
    //   300: aastore
    //   301: dup_x2
    //   302: dup_x2
    //   303: pop
    //   304: invokestatic valueOf : (J)Ljava/lang/Long;
    //   307: iconst_0
    //   308: swap
    //   309: aastore
    //   310: invokestatic Z : ([Ljava/lang/Object;)Z
    //   313: lload #7
    //   315: lconst_0
    //   316: lcmp
    //   317: iflt -> 429
    //   320: ifeq -> 427
    //   323: goto -> 330
    //   326: invokestatic a : (Lwtf/opal/x5;)Lwtf/opal/x5;
    //   329: athrow
    //   330: aload #16
    //   332: iconst_1
    //   333: iconst_1
    //   334: anewarray java/lang/Object
    //   337: dup_x1
    //   338: swap
    //   339: invokestatic valueOf : (Z)Ljava/lang/Boolean;
    //   342: iconst_0
    //   343: swap
    //   344: aastore
    //   345: invokevirtual H : ([Ljava/lang/Object;)V
    //   348: aload #16
    //   350: dload_3
    //   351: aload #16
    //   353: lload #11
    //   355: iconst_1
    //   356: anewarray java/lang/Object
    //   359: dup_x2
    //   360: dup_x2
    //   361: pop
    //   362: invokestatic valueOf : (J)Ljava/lang/Long;
    //   365: iconst_0
    //   366: swap
    //   367: aastore
    //   368: invokevirtual t : ([Ljava/lang/Object;)F
    //   371: f2d
    //   372: dsub
    //   373: d2f
    //   374: iconst_1
    //   375: anewarray java/lang/Object
    //   378: dup_x1
    //   379: swap
    //   380: invokestatic valueOf : (F)Ljava/lang/Float;
    //   383: iconst_0
    //   384: swap
    //   385: aastore
    //   386: invokevirtual u : ([Ljava/lang/Object;)V
    //   389: aload #16
    //   391: goto -> 398
    //   394: invokestatic a : (Lwtf/opal/x5;)Lwtf/opal/x5;
    //   397: athrow
    //   398: dload #5
    //   400: aload #16
    //   402: iconst_0
    //   403: anewarray java/lang/Object
    //   406: invokevirtual x : ([Ljava/lang/Object;)F
    //   409: f2d
    //   410: dsub
    //   411: d2f
    //   412: iconst_1
    //   413: anewarray java/lang/Object
    //   416: dup_x1
    //   417: swap
    //   418: invokestatic valueOf : (F)Ljava/lang/Float;
    //   421: iconst_0
    //   422: swap
    //   423: aastore
    //   424: invokevirtual e : ([Ljava/lang/Object;)V
    //   427: iload #13
    //   429: ifeq -> 99
    //   432: return
    // Exception table:
    //   from	to	target	type
    //   74	79	79	wtf/opal/x5
    //   121	160	163	wtf/opal/x5
    //   143	174	177	wtf/opal/x5
    //   186	323	326	wtf/opal/x5
    //   193	391	394	wtf/opal/x5
  }
  
  public void T(Object[] paramArrayOfObject) {
    long l = ((Long)paramArrayOfObject[0]).longValue();
    int i = ((Integer)paramArrayOfObject[1]).intValue();
    l = a ^ l;
    try {
      if (i == 0)
        this.X.forEach(lj::lambda$mouseReleased$0); 
    } catch (x5 x5) {
      throw a(null);
    } 
  }
  
  private static void lambda$mouseReleased$0(k6 paramk6, d paramd) {
    paramk6.H(new Object[] { Boolean.valueOf(false) });
  }
  
  static {
    long l = a ^ 0x3E06328EB82AL;
    (new byte[8])[0] = (byte)(int)(l >>> 56L);
    for (byte b = 1; b < 8; b++)
      (new byte[8])[b] = (byte)(int)(l << b * 8 >>> 56L); 
    Cipher cipher;
    (cipher = Cipher.getInstance("DES/CBC/NoPadding")).init(2, SecretKeyFactory.getInstance("DES").generateSecret(new DESKeySpec(new byte[8])), new IvParameterSpec(new byte[8]));
  }
  
  private static x5 a(x5 paramx5) {
    return paramx5;
  }
}


/* Location:              C:\Users\Administrator\Downloads\Opal 080624 ez\Opal.jar!\wtf\opal\lj.class
 * Java compiler version: 21 (65.0)
 * JD-Core Version:       1.1.3
 */