package wtf.opal;

import java.lang.invoke.MethodHandles;

public final class p2 extends u_<xw> {
  private final gm<b6> u = this::lambda$new$0;
  
  private static final long a = on.a(8004043641189343478L, 3555697160821701353L, MethodHandles.lookup().lookupClass()).a(40980668857594L);
  
  public p2(xw paramxw) {
    super(paramxw);
  }
  
  public Enum V(Object[] paramArrayOfObject) {
    return l1.EXPERIMENTAL;
  }
  
  private void lambda$new$0(b6 paramb6) {
    // Byte code:
    //   0: getstatic wtf/opal/p2.a : J
    //   3: ldc2_w 69328225876181
    //   6: lxor
    //   7: lstore_2
    //   8: lload_2
    //   9: dup2
    //   10: ldc2_w 51432135500170
    //   13: lxor
    //   14: lstore #4
    //   16: pop2
    //   17: invokestatic D : ()Z
    //   20: istore #6
    //   22: aload_1
    //   23: iconst_0
    //   24: anewarray java/lang/Object
    //   27: invokevirtual W : ([Ljava/lang/Object;)Z
    //   30: iload #6
    //   32: ifne -> 64
    //   35: ifeq -> 112
    //   38: goto -> 45
    //   41: invokestatic b : (Lwtf/opal/x5;)Lwtf/opal/x5;
    //   44: athrow
    //   45: getstatic wtf/opal/b9.c : Lnet/minecraft/class_310;
    //   48: getfield field_1690 : Lnet/minecraft/class_315;
    //   51: getfield field_1903 : Lnet/minecraft/class_304;
    //   54: invokevirtual method_1434 : ()Z
    //   57: goto -> 64
    //   60: invokestatic b : (Lwtf/opal/x5;)Lwtf/opal/x5;
    //   63: athrow
    //   64: iload #6
    //   66: ifne -> 109
    //   69: ifeq -> 112
    //   72: goto -> 79
    //   75: invokestatic b : (Lwtf/opal/x5;)Lwtf/opal/x5;
    //   78: athrow
    //   79: aload_0
    //   80: iconst_0
    //   81: anewarray java/lang/Object
    //   84: invokevirtual y : ([Ljava/lang/Object;)Lwtf/opal/d;
    //   87: checkcast wtf/opal/xw
    //   90: getfield B : Lwtf/opal/ke;
    //   93: invokevirtual z : ()Ljava/lang/Object;
    //   96: checkcast java/lang/Boolean
    //   99: invokevirtual booleanValue : ()Z
    //   102: goto -> 109
    //   105: invokestatic b : (Lwtf/opal/x5;)Lwtf/opal/x5;
    //   108: athrow
    //   109: ifne -> 113
    //   112: return
    //   113: getstatic wtf/opal/b9.c : Lnet/minecraft/class_310;
    //   116: getfield field_1724 : Lnet/minecraft/class_746;
    //   119: invokevirtual method_23318 : ()D
    //   122: getstatic wtf/opal/b9.c : Lnet/minecraft/class_310;
    //   125: getfield field_1724 : Lnet/minecraft/class_746;
    //   128: invokevirtual method_23318 : ()D
    //   131: invokestatic floor : (D)D
    //   134: dsub
    //   135: lload #4
    //   137: dup2_x2
    //   138: pop2
    //   139: iconst_3
    //   140: iconst_3
    //   141: anewarray java/lang/Object
    //   144: dup_x1
    //   145: swap
    //   146: invokestatic valueOf : (I)Ljava/lang/Integer;
    //   149: iconst_2
    //   150: swap
    //   151: aastore
    //   152: dup_x2
    //   153: dup_x2
    //   154: pop
    //   155: invokestatic valueOf : (D)Ljava/lang/Double;
    //   158: iconst_1
    //   159: swap
    //   160: aastore
    //   161: dup_x2
    //   162: dup_x2
    //   163: pop
    //   164: invokestatic valueOf : (J)Ljava/lang/Long;
    //   167: iconst_0
    //   168: swap
    //   169: aastore
    //   170: invokestatic P : ([Ljava/lang/Object;)D
    //   173: dstore #7
    //   175: dload #7
    //   177: dconst_0
    //   178: dcmpl
    //   179: iload #6
    //   181: ifne -> 246
    //   184: ifne -> 233
    //   187: goto -> 194
    //   190: invokestatic b : (Lwtf/opal/x5;)Lwtf/opal/x5;
    //   193: athrow
    //   194: getstatic wtf/opal/b9.c : Lnet/minecraft/class_310;
    //   197: getfield field_1724 : Lnet/minecraft/class_746;
    //   200: getstatic wtf/opal/b9.c : Lnet/minecraft/class_310;
    //   203: getfield field_1724 : Lnet/minecraft/class_746;
    //   206: invokevirtual method_18798 : ()Lnet/minecraft/class_243;
    //   209: getstatic net/minecraft/class_2350$class_2351.field_11052 : Lnet/minecraft/class_2350$class_2351;
    //   212: ldc2_w 0.41999998688697815
    //   215: invokevirtual method_38499 : (Lnet/minecraft/class_2350$class_2351;D)Lnet/minecraft/class_243;
    //   218: invokevirtual method_18799 : (Lnet/minecraft/class_243;)V
    //   221: iload #6
    //   223: ifeq -> 415
    //   226: goto -> 233
    //   229: invokestatic b : (Lwtf/opal/x5;)Lwtf/opal/x5;
    //   232: athrow
    //   233: dload #7
    //   235: ldc2_w 0.42
    //   238: dcmpl
    //   239: goto -> 246
    //   242: invokestatic b : (Lwtf/opal/x5;)Lwtf/opal/x5;
    //   245: athrow
    //   246: iload #6
    //   248: ifne -> 313
    //   251: ifne -> 300
    //   254: goto -> 261
    //   257: invokestatic b : (Lwtf/opal/x5;)Lwtf/opal/x5;
    //   260: athrow
    //   261: getstatic wtf/opal/b9.c : Lnet/minecraft/class_310;
    //   264: getfield field_1724 : Lnet/minecraft/class_746;
    //   267: getstatic wtf/opal/b9.c : Lnet/minecraft/class_310;
    //   270: getfield field_1724 : Lnet/minecraft/class_746;
    //   273: invokevirtual method_18798 : ()Lnet/minecraft/class_243;
    //   276: getstatic net/minecraft/class_2350$class_2351.field_11052 : Lnet/minecraft/class_2350$class_2351;
    //   279: ldc2_w 0.3330000042915344
    //   282: invokevirtual method_38499 : (Lnet/minecraft/class_2350$class_2351;D)Lnet/minecraft/class_243;
    //   285: invokevirtual method_18799 : (Lnet/minecraft/class_243;)V
    //   288: iload #6
    //   290: ifeq -> 415
    //   293: goto -> 300
    //   296: invokestatic b : (Lwtf/opal/x5;)Lwtf/opal/x5;
    //   299: athrow
    //   300: dload #7
    //   302: ldc2_w 0.753
    //   305: dcmpl
    //   306: goto -> 313
    //   309: invokestatic b : (Lwtf/opal/x5;)Lwtf/opal/x5;
    //   312: athrow
    //   313: iload #6
    //   315: ifne -> 378
    //   318: ifne -> 367
    //   321: goto -> 328
    //   324: invokestatic b : (Lwtf/opal/x5;)Lwtf/opal/x5;
    //   327: athrow
    //   328: getstatic wtf/opal/b9.c : Lnet/minecraft/class_310;
    //   331: getfield field_1724 : Lnet/minecraft/class_746;
    //   334: getstatic wtf/opal/b9.c : Lnet/minecraft/class_310;
    //   337: getfield field_1724 : Lnet/minecraft/class_746;
    //   340: invokevirtual method_18798 : ()Lnet/minecraft/class_243;
    //   343: getstatic net/minecraft/class_2350$class_2351.field_11052 : Lnet/minecraft/class_2350$class_2351;
    //   346: ldc2_w 0.24690000712871552
    //   349: invokevirtual method_38499 : (Lnet/minecraft/class_2350$class_2351;D)Lnet/minecraft/class_243;
    //   352: invokevirtual method_18799 : (Lnet/minecraft/class_243;)V
    //   355: iload #6
    //   357: ifeq -> 415
    //   360: goto -> 367
    //   363: invokestatic b : (Lwtf/opal/x5;)Lwtf/opal/x5;
    //   366: athrow
    //   367: dload #7
    //   369: dconst_1
    //   370: dcmpl
    //   371: goto -> 378
    //   374: invokestatic b : (Lwtf/opal/x5;)Lwtf/opal/x5;
    //   377: athrow
    //   378: ifne -> 415
    //   381: getstatic wtf/opal/b9.c : Lnet/minecraft/class_310;
    //   384: getfield field_1724 : Lnet/minecraft/class_746;
    //   387: getstatic wtf/opal/b9.c : Lnet/minecraft/class_310;
    //   390: getfield field_1724 : Lnet/minecraft/class_746;
    //   393: invokevirtual method_18798 : ()Lnet/minecraft/class_243;
    //   396: getstatic net/minecraft/class_2350$class_2351.field_11052 : Lnet/minecraft/class_2350$class_2351;
    //   399: ldc2_w 0.10000000149011612
    //   402: invokevirtual method_38499 : (Lnet/minecraft/class_2350$class_2351;D)Lnet/minecraft/class_243;
    //   405: invokevirtual method_18799 : (Lnet/minecraft/class_243;)V
    //   408: goto -> 415
    //   411: invokestatic b : (Lwtf/opal/x5;)Lwtf/opal/x5;
    //   414: athrow
    //   415: return
    // Exception table:
    //   from	to	target	type
    //   22	38	41	wtf/opal/x5
    //   35	57	60	wtf/opal/x5
    //   64	72	75	wtf/opal/x5
    //   69	102	105	wtf/opal/x5
    //   175	187	190	wtf/opal/x5
    //   184	226	229	wtf/opal/x5
    //   194	239	242	wtf/opal/x5
    //   246	254	257	wtf/opal/x5
    //   251	293	296	wtf/opal/x5
    //   261	306	309	wtf/opal/x5
    //   313	321	324	wtf/opal/x5
    //   318	360	363	wtf/opal/x5
    //   328	371	374	wtf/opal/x5
    //   378	408	411	wtf/opal/x5
  }
  
  private static x5 b(x5 paramx5) {
    return paramx5;
  }
}


/* Location:              C:\Users\Administrator\Downloads\Opal 080624 ez\Opal.jar!\wtf\opal\p2.class
 * Java compiler version: 21 (65.0)
 * JD-Core Version:       1.1.3
 */