package wtf.opal;

import java.lang.invoke.MethodHandles;

public final class ua extends u_<jm> {
  private final gm<b6> R = ua::lambda$new$0;
  
  private static final long a = on.a(2669032582504483815L, 2776679560411945771L, MethodHandles.lookup().lookupClass()).a(31611639017277L);
  
  public ua(jm paramjm) {
    super(paramjm);
  }
  
  public Enum V(Object[] paramArrayOfObject) {
    return bn.STRAFE;
  }
  
  private static void lambda$new$0(b6 paramb6) {
    // Byte code:
    //   0: getstatic wtf/opal/ua.a : J
    //   3: ldc2_w 53111692526595
    //   6: lxor
    //   7: lstore_1
    //   8: lload_1
    //   9: dup2
    //   10: ldc2_w 85102381394902
    //   13: lxor
    //   14: lstore_3
    //   15: dup2
    //   16: ldc2_w 113143493411650
    //   19: lxor
    //   20: lstore #5
    //   22: pop2
    //   23: invokestatic k : ()I
    //   26: istore #7
    //   28: aload_0
    //   29: iconst_0
    //   30: anewarray java/lang/Object
    //   33: invokevirtual W : ([Ljava/lang/Object;)Z
    //   36: iload #7
    //   38: ifeq -> 75
    //   41: ifeq -> 90
    //   44: goto -> 51
    //   47: invokestatic b : (Lwtf/opal/x5;)Lwtf/opal/x5;
    //   50: athrow
    //   51: lload_3
    //   52: iconst_1
    //   53: anewarray java/lang/Object
    //   56: dup_x2
    //   57: dup_x2
    //   58: pop
    //   59: invokestatic valueOf : (J)Ljava/lang/Long;
    //   62: iconst_0
    //   63: swap
    //   64: aastore
    //   65: invokestatic I : ([Ljava/lang/Object;)Z
    //   68: goto -> 75
    //   71: invokestatic b : (Lwtf/opal/x5;)Lwtf/opal/x5;
    //   74: athrow
    //   75: iload #7
    //   77: ifeq -> 112
    //   80: ifne -> 91
    //   83: goto -> 90
    //   86: invokestatic b : (Lwtf/opal/x5;)Lwtf/opal/x5;
    //   89: athrow
    //   90: return
    //   91: getstatic wtf/opal/b9.c : Lnet/minecraft/class_310;
    //   94: getfield field_1724 : Lnet/minecraft/class_746;
    //   97: iload #7
    //   99: ifeq -> 128
    //   102: invokevirtual method_24828 : ()Z
    //   105: goto -> 112
    //   108: invokestatic b : (Lwtf/opal/x5;)Lwtf/opal/x5;
    //   111: athrow
    //   112: ifeq -> 131
    //   115: getstatic wtf/opal/b9.c : Lnet/minecraft/class_310;
    //   118: getfield field_1724 : Lnet/minecraft/class_746;
    //   121: goto -> 128
    //   124: invokestatic b : (Lwtf/opal/x5;)Lwtf/opal/x5;
    //   127: athrow
    //   128: invokevirtual method_6043 : ()V
    //   131: iconst_0
    //   132: anewarray java/lang/Object
    //   135: invokestatic U : ([Ljava/lang/Object;)F
    //   138: f2d
    //   139: lload #5
    //   141: dup2_x2
    //   142: pop2
    //   143: iconst_2
    //   144: anewarray java/lang/Object
    //   147: dup_x2
    //   148: dup_x2
    //   149: pop
    //   150: invokestatic valueOf : (D)Ljava/lang/Double;
    //   153: iconst_1
    //   154: swap
    //   155: aastore
    //   156: dup_x2
    //   157: dup_x2
    //   158: pop
    //   159: invokestatic valueOf : (J)Ljava/lang/Long;
    //   162: iconst_0
    //   163: swap
    //   164: aastore
    //   165: invokestatic k : ([Ljava/lang/Object;)V
    //   168: return
    // Exception table:
    //   from	to	target	type
    //   28	44	47	wtf/opal/x5
    //   41	68	71	wtf/opal/x5
    //   75	83	86	wtf/opal/x5
    //   91	105	108	wtf/opal/x5
    //   112	121	124	wtf/opal/x5
  }
  
  private static x5 b(x5 paramx5) {
    return paramx5;
  }
}


/* Location:              C:\Users\Administrator\Downloads\Opal 080624 ez\Opal.jar!\wtf\opa\\ua.class
 * Java compiler version: 21 (65.0)
 * JD-Core Version:       1.1.3
 */